{"images":[{"status":"Complete","width":1344,"height":2500,"file":"DwgoKCCKjJ-xqqvMLYHI5x_A81M-vJ3v9_QDGXol4iKw_mhAlTaPeciuNyQl-aAa1HAfNEA0XcOOncHHpIxx36fxC-A=s0","faces":[{"topLeftX":856,"topLeftY":1326,"chinTipX":893,"rightEyeCenterX":877,"yaw":-26,"chinTipY":1399,"confidence":0.99912,"height":71,"rightEyeCenterY":1344,"width":71,"leftEyeCenterY":1345,"leftEyeCenterX":907,"pitch":-16,"attributes":{"lips":"Together","asian":0.01789,"gender":{"type":"F"},"age":31,"hispanic":0.08504,"other":0.00745,"black":0.00508,"white":0.88454,"glasses":"None"},"face_id":1,"quality":-1.82084,"roll":0},{"topLeftX":1137,"topLeftY":1272,"chinTipX":1173,"rightEyeCenterX":1155,"yaw":23,"chinTipY":1349,"confidence":0.99761,"height":74,"rightEyeCenterY":1293,"width":74,"leftEyeCenterY":1292,"leftEyeCenterX":1184,"pitch":-37,"attributes":{"lips":"Together","asian":0.00112,"gender":{"type":"M"},"age":34,"hispanic":0.01748,"other":0.00177,"black":0.00164,"white":0.97799,"glasses":"Eye"},"face_id":2,"quality":-0.54124,"roll":-4},{"topLeftX":1233,"topLeftY":1341,"chinTipX":1272,"rightEyeCenterX":1251,"yaw":33,"chinTipY":1415,"confidence":0.9974,"height":62,"rightEyeCenterY":1358,"width":62,"leftEyeCenterY":1354,"leftEyeCenterX":1277,"pitch":-9,"attributes":{"lips":"Apart","asian":0.00098,"gender":{"type":"F"},"age":33,"hispanic":0.04627,"other":0.00706,"black":0.00324,"white":0.94246,"glasses":"None"},"face_id":3,"quality":-2.44283,"roll":-8},{"topLeftX":785,"topLeftY":1356,"chinTipX":816,"rightEyeCenterX":809,"yaw":-23,"chinTipY":1428,"confidence":0.99696,"height":74,"rightEyeCenterY":1374,"width":74,"leftEyeCenterY":1377,"leftEyeCenterX":838,"pitch":-23,"attributes":{"lips":"Together","asian":0.00175,"gender":{"type":"M"},"age":35,"hispanic":0.08738,"other":0.00312,"black":0.00127,"white":0.90648,"glasses":"Eye"},"face_id":4,"quality":-2.11378,"roll":8},{"topLeftX":1088,"topLeftY":1408,"chinTipX":1130,"rightEyeCenterX":1111,"yaw":27,"chinTipY":1493,"confidence":0.99609,"height":78,"rightEyeCenterY":1426,"width":78,"leftEyeCenterY":1426,"leftEyeCenterX":1144,"pitch":-3,"attributes":{"lips":"Together","asian":0.00347,"gender":{"type":"M"},"age":37,"hispanic":0.13811,"other":0.00485,"black":0.00108,"white":0.85248,"glasses":"None"},"face_id":5,"quality":-1.39602,"roll":-2}]}]}