{"images":[{"status":"Complete","width":2944,"height":1988,"file":"rhoR3gzbi-YeF2mIiVhb85zrne2TnSRSvS-NoNGCWWtr41l4iNQMPJmRgj8nB4OwXMrNjjJEc8crmYYJ6sVq8UG4X4jC=s0","faces":[{"topLeftX":1392,"topLeftY":152,"chinTipX":1416,"rightEyeCenterX":1406,"yaw":5,"chinTipY":201,"confidence":0.98666,"height":52,"rightEyeCenterY":163,"width":52,"leftEyeCenterY":162,"leftEyeCenterX":1425,"pitch":-20,"attributes":{"lips":"Together","asian":0.08083,"gender":{"type":"M"},"age":39,"hispanic":0.21379,"other":0.09846,"black":0.0827,"white":0.52422,"glasses":"Eye"},"face_id":1,"quality":-1.73586,"roll":-1}]}]}