{"images":[{"status":"Complete","width":2488,"height":2604,"file":"DlP_bLkDQc79U0QVNhsU2gL8CIqR_vxeK2tecy5aXLq-GlrSBc9o_AWeyEkmgwFBWNoKpqyss51KJHOJF_EGcnbh6Q=s0","faces":[{"topLeftX":538,"topLeftY":1243,"chinTipX":666,"rightEyeCenterX":585,"yaw":-10,"chinTipY":1425,"confidence":0.99859,"height":186,"rightEyeCenterY":1307,"width":185,"leftEyeCenterY":1284,"leftEyeCenterX":666,"pitch":-12,"attributes":{"lips":"Together","asian":0.00607,"gender":{"type":"F"},"age":42,"hispanic":0.09807,"other":0.07135,"black":0.03867,"white":0.78585,"glasses":"None"},"face_id":1,"quality":-1.68823,"roll":-17}]}]}