{"images":[{"status":"Complete","width":1867,"height":2500,"file":"Dlf9DICu0ficdHAZgXJZllojozQuS1XssMpQbP8XP5CrRyIdq50DM_U7RvJBAd3aGaaO6pGGcwG3QUDTX9jECWhjdw=s0","faces":[{"topLeftX":809,"topLeftY":655,"chinTipX":1328,"rightEyeCenterX":1050,"yaw":-34,"chinTipY":1519,"confidence":0.9993,"height":837,"rightEyeCenterY":903,"width":837,"leftEyeCenterY":856,"leftEyeCenterX":1396,"pitch":-26,"attributes":{"lips":"Together","asian":0.00027,"gender":{"type":"M"},"age":35,"hispanic":0.01854,"other":0.00104,"black":0.00025,"white":0.9799,"glasses":"None"},"face_id":1,"quality":-1.80248,"roll":-9}]}]}