{"images":[{"status":"Complete","width":1916,"height":2500,"file":"s_32ZlJiUoeQSiEwKF-cAP_QFhCNWvqzvKClbwpC6A_r-ziJvJumqG_8OPrdts4RPkOEwvZNSwV-jbcMM8GkYXdftJPy=s0","faces":[{"topLeftX":314,"topLeftY":1114,"chinTipX":339,"rightEyeCenterX":338,"yaw":-36,"chinTipY":1175,"confidence":0.99899,"height":62,"rightEyeCenterY":1131,"width":62,"leftEyeCenterY":1136,"leftEyeCenterX":359,"pitch":-7,"attributes":{"lips":"Together","asian":0.31631,"gender":{"type":"F"},"age":30,"hispanic":0.19766,"other":0.16145,"black":0.15509,"white":0.1695,"glasses":"Sun"},"face_id":1,"quality":-0.35121,"roll":13},{"topLeftX":19,"topLeftY":1169,"chinTipX":46,"rightEyeCenterX":39,"yaw":-20,"chinTipY":1233,"confidence":0.99362,"height":62,"rightEyeCenterY":1184,"width":62,"leftEyeCenterY":1186,"leftEyeCenterX":61,"pitch":-2,"attributes":{"lips":"Apart","asian":0.01974,"gender":{"type":"M"},"age":39,"hispanic":0.13784,"other":0.01096,"black":0.00156,"white":0.8299,"glasses":"None"},"face_id":2,"quality":-1.62737,"roll":5}]}]}