{"images":[{"status":"Complete","width":2058,"height":2500,"file":"z0M6ix_AH08vLPD-w0rZSeRI25sv9U8egkJpU7WDchpDXqcRy5zIADdkkate4CcboB2ScXxquKokSDZpfMRuJ19KtuM=s0","faces":[{"topLeftX":1107,"topLeftY":697,"chinTipX":1234,"rightEyeCenterX":1163,"yaw":33,"chinTipY":957,"confidence":0.99992,"height":253,"rightEyeCenterY":771,"width":253,"leftEyeCenterY":759,"leftEyeCenterX":1259,"pitch":-8,"attributes":{"lips":"Apart","asian":0.00626,"gender":{"type":"F"},"age":29,"hispanic":0.04242,"other":0.01827,"black":0.0032,"white":0.92985,"glasses":"None"},"face_id":1,"quality":-0.44046,"roll":-7},{"topLeftX":502,"topLeftY":514,"chinTipX":591,"rightEyeCenterX":610,"yaw":-45,"chinTipY":759,"confidence":0.99598,"height":229,"rightEyeCenterY":565,"width":229,"leftEyeCenterY":600,"leftEyeCenterX":705,"pitch":6,"attributes":{"lips":"Together","asian":0.01445,"gender":{"type":"M"},"age":23,"hispanic":0.3625,"other":0.05111,"black":0.00569,"white":0.56625,"glasses":"None"},"face_id":2,"quality":-2.05867,"roll":20}]}]}