{"images":[{"status":"Complete","width":2088,"height":2452,"file":"kIOMaziK-23M_cnCL4lYcWQozBSRvht7xWScDm7s0glQTSsfgsX1KSxS6jMtLD6_7e94vb1o0iM7BFUz2IsjM1SAN3Y=s0","faces":[{"topLeftX":1019,"topLeftY":508,"chinTipX":1085,"rightEyeCenterX":1118,"yaw":-27,"chinTipY":683,"confidence":0.98491,"height":171,"rightEyeCenterY":549,"width":171,"leftEyeCenterY":584,"leftEyeCenterX":1175,"pitch":16,"attributes":{"lips":"Apart","asian":0.01551,"gender":{"type":"M"},"age":31,"hispanic":0.13817,"other":0.03817,"black":0.0666,"white":0.74155,"glasses":"None"},"face_id":1,"quality":-1.38745,"roll":28}]}]}