{"images":[{"status":"Complete","width":2059,"height":2500,"file":"Dyb4gLT3gngQql_J4YEjWXKfhHIXXZ1gGHVU4-DyC0Vi5Dd8vq0eTWMp98O7zZnxcNdb1lfkwUGz1sC3h9ZB_VHwcQE=s0","faces":[{"topLeftX":871,"topLeftY":871,"chinTipX":1095,"rightEyeCenterX":988,"yaw":-20,"chinTipY":1293,"confidence":0.99987,"height":391,"rightEyeCenterY":982,"width":392,"leftEyeCenterY":979,"leftEyeCenterX":1151,"pitch":-16,"attributes":{"lips":"Apart","asian":0.0014,"gender":{"type":"M"},"age":24,"hispanic":0.09931,"other":0.00539,"black":0.00026,"white":0.89363,"glasses":"None"},"face_id":1,"quality":0.68302,"roll":-5}]}]}