{"images":[{"status":"Complete","width":2500,"height":2010,"file":"UtbXWbBX76jKJtfp-X0J9bwSLKoDH__n-_2E_4iGSxgcDXAqUYTa55t6cxwTv5Kc-B_0wlJaVDHkn7ba9szMTyu0_E8D=s0","faces":[{"topLeftX":1007,"topLeftY":1054,"chinTipX":1045,"rightEyeCenterX":1025,"yaw":13,"chinTipY":1122,"confidence":0.99533,"height":68,"rightEyeCenterY":1072,"width":68,"leftEyeCenterY":1070,"leftEyeCenterX":1053,"pitch":-24,"attributes":{"lips":"Together","asian":0.00624,"gender":{"type":"M"},"age":40,"hispanic":0.24323,"other":0.03499,"black":0.00435,"white":0.71119,"glasses":"None"},"face_id":1,"quality":-1.8978,"roll":-7}]}]}