{"images":[{"status":"Complete","width":3000,"height":888,"file":"s5M3_SOmLVp0E62dov8b7GjL87ibyZg3tW-YLU4EPz9lAnehWIw7a6gVqxjEbpNBHnYbw2rUu6YORl0AQE-rSiBk9Ec=s0","faces":[{"topLeftX":2027,"topLeftY":119,"chinTipX":2049,"rightEyeCenterX":2042,"yaw":15,"chinTipY":164,"confidence":0.98273,"height":45,"rightEyeCenterY":130,"width":45,"leftEyeCenterY":129,"leftEyeCenterX":2061,"pitch":1,"attributes":{"lips":"Together","asian":0.16667,"gender":{"type":"M"},"age":38,"hispanic":0.0448,"other":0.0701,"black":0.67568,"white":0.04274,"glasses":"None"},"face_id":1,"quality":-2.47501,"roll":5}]}]}