{"images":[{"status":"Complete","width":1860,"height":2580,"file":"y-4Kp-cdVMFPeZd2JpEhdQOalno06lKhtnyvoRqyExhu--B-_lhMjHIQr5WUjTN_laf99W_ylaut9Anu6jlZvlIrzBw=s0","faces":[{"topLeftX":615,"topLeftY":378,"chinTipX":782,"rightEyeCenterX":724,"yaw":32,"chinTipY":737,"confidence":0.99997,"height":342,"rightEyeCenterY":467,"width":342,"leftEyeCenterY":458,"leftEyeCenterX":864,"pitch":2,"attributes":{"lips":"Together","asian":0.00549,"gender":{"type":"M"},"age":27,"hispanic":0.40956,"other":0.01823,"black":0.0141,"white":0.55263,"glasses":"None"},"face_id":1,"quality":-0.92184,"roll":2}]}]}