{"images":[{"status":"Complete","width":1919,"height":2412,"file":"vwQf-1e1b4u0EFiO3-pU53oM50uZPhVHFkVJUC_PofQaZ0EqaMYRm9dS9812eiFXqI7OXhTdMxQ3WeKXbPXPMOrP-M4=s0","faces":[{"topLeftX":640,"topLeftY":716,"chinTipX":839,"rightEyeCenterX":770,"yaw":15,"chinTipY":1154,"confidence":0.99995,"height":451,"rightEyeCenterY":830,"width":451,"leftEyeCenterY":835,"leftEyeCenterX":953,"pitch":-22,"attributes":{"lips":"Together","asian":0.01371,"gender":{"type":"F"},"age":23,"hispanic":0.11329,"other":0.00525,"black":0.00374,"white":0.86401,"glasses":"None"},"face_id":1,"quality":-0.51894,"roll":4}]}]}