{"images":[{"status":"Complete","width":2112,"height":2670,"file":"Ft4F_CWpb6s_Q4Xu0_Qs6myUy1ZH_-PTMpmcd-E3sqsJwxj-OoUBb8hdSRZxO9wuPxmCstWTo3q9eAB46r4woGs6MRMg=s0","faces":[{"topLeftX":889,"topLeftY":780,"chinTipX":1330,"rightEyeCenterX":1056,"yaw":-24,"chinTipY":1538,"confidence":0.99871,"height":674,"rightEyeCenterY":956,"width":674,"leftEyeCenterY":928,"leftEyeCenterX":1369,"pitch":1,"attributes":{"lips":"Together","asian":0.00319,"gender":{"type":"M"},"age":59,"hispanic":0.04539,"other":0.00181,"black":0.80315,"white":0.14646,"glasses":"None"},"face_id":1,"quality":-1.19119,"roll":-11}]}]}