{"images":[{"status":"Complete","width":2254,"height":2622,"file":"3oF0m7SlWkHd1N5bI0nzoi3GTvF9z7CKfSCzq91ZOTMsOErpFnedMmpQyil5ICN6_-Hvtkjjz1simrp4uqndO2ZHhwg=s0","faces":[{"topLeftX":1064,"topLeftY":528,"chinTipX":1187,"rightEyeCenterX":1148,"yaw":37,"chinTipY":804,"confidence":0.99986,"height":271,"rightEyeCenterY":597,"width":271,"leftEyeCenterY":601,"leftEyeCenterX":1256,"pitch":-11,"attributes":{"lips":"Together","asian":0.00643,"gender":{"type":"F"},"age":28,"hispanic":0.18969,"other":0.00961,"black":0.00646,"white":0.78781,"glasses":"None"},"face_id":1,"quality":-0.87467,"roll":4}]}]}