{"images":[{"status":"Complete","width":2074,"height":2580,"file":"E42YzmbW6gt7su5LZtGqCbSyHK795kE9rf6NA_D7X9-PYS5eXnSEl7bBLHdAchxLu_CxmXm-W_2Fgcw7Yb6PAGtkRPA=s0","faces":[{"topLeftX":842,"topLeftY":385,"chinTipX":1002,"rightEyeCenterX":916,"yaw":-12,"chinTipY":700,"confidence":0.9993,"height":280,"rightEyeCenterY":457,"width":280,"leftEyeCenterY":448,"leftEyeCenterX":1036,"pitch":-17,"attributes":{"lips":"Together","asian":0.00101,"gender":{"type":"M"},"age":37,"hispanic":0.01505,"other":0.00202,"black":0.00034,"white":0.98158,"glasses":"None"},"face_id":1,"quality":0.05003,"roll":-6}]}]}