{"images":[{"status":"Complete","width":2028,"height":2500,"file":"-o4uQjOq-4EhJjW2DfeDyosGLdP1-34iJUirdb9h0-2n3sY0-ZrvabwLfBXY3lK7CDorr5iKyOdG7XFMo0sG6dOVAw=s0","faces":[{"topLeftX":917,"topLeftY":652,"chinTipX":1200,"rightEyeCenterX":1071,"yaw":-17,"chinTipY":1270,"confidence":0.99962,"height":535,"rightEyeCenterY":781,"width":535,"leftEyeCenterY":780,"leftEyeCenterX":1295,"pitch":-13,"attributes":{"lips":"Together","asian":0.00036,"gender":{"type":"M"},"age":57,"hispanic":0.01929,"other":0.00049,"black":0.00036,"white":0.97949,"glasses":"None"},"face_id":1,"quality":-0.15247,"roll":-2}]}]}