{"images":[{"status":"Complete","width":2896,"height":2136,"file":"BoBSf5kcicgsB9kGjem3MsHGAv_G1tVplYhRSbdhNqhWqoG6ky9vnC6cigSwUmhz-xMRlIpaPV_7W9qrfYkn1WGd0h8=s0","faces":[{"topLeftX":1994,"topLeftY":1320,"chinTipX":2016,"rightEyeCenterX":2010,"yaw":11,"chinTipY":1373,"confidence":0.9983,"height":51,"rightEyeCenterY":1330,"width":51,"leftEyeCenterY":1332,"leftEyeCenterX":2030,"pitch":-3,"attributes":{"lips":"Together","asian":0.00086,"gender":{"type":"M"},"age":32,"hispanic":0.02925,"other":0.00838,"black":0.1347,"white":0.82681,"glasses":"None"},"face_id":1,"quality":-1.37878,"roll":6},{"topLeftX":1187,"topLeftY":2052,"chinTipX":1209,"rightEyeCenterX":1199,"yaw":-3,"chinTipY":2096,"confidence":0.98711,"height":43,"rightEyeCenterY":2060,"width":43,"leftEyeCenterY":2061,"leftEyeCenterX":1218,"pitch":-8,"attributes":{"lips":"Apart","asian":0.01422,"gender":{"type":"F"},"age":41,"hispanic":0.12966,"other":0.00644,"black":0.8236,"white":0.02608,"glasses":"None"},"face_id":2,"quality":-1.74948,"roll":0}]}]}