{"images":[{"status":"Complete","width":1991,"height":2564,"file":"2gT1jbghqGWze-On1ygZclQjedGskFmUzOnBg-i501vZpUkwWw1eA_KWat0Ucrvztkh_GKw9CJQ3PHbVzvdBJi7vu0A=s0","faces":[{"topLeftX":799,"topLeftY":620,"chinTipX":933,"rightEyeCenterX":886,"yaw":3,"chinTipY":892,"confidence":0.9999,"height":265,"rightEyeCenterY":680,"width":265,"leftEyeCenterY":686,"leftEyeCenterX":996,"pitch":-15,"attributes":{"lips":"Together","asian":7.0e-5,"gender":{"type":"F"},"age":38,"hispanic":0.00192,"other":2.0e-5,"black":0,"white":0.998,"glasses":"None"},"face_id":1,"quality":0.9404,"roll":2}]}]}