{"images":[{"status":"Complete","width":1469,"height":2592,"file":"ajBrFAw6EKZtX6n1DFcTI2CbrVZTQ3o2WOPoam-ID51GlEO9jN4vZCRs3CGAFn2E16qYphtVd3CReTJDqSQ3OCpucXE=s0","faces":[{"topLeftX":600,"topLeftY":506,"chinTipX":685,"rightEyeCenterX":649,"yaw":28,"chinTipY":680,"confidence":0.9995,"height":163,"rightEyeCenterY":544,"width":163,"leftEyeCenterY":545,"leftEyeCenterX":720,"pitch":-18,"attributes":{"lips":"Together","asian":2.0e-5,"gender":{"type":"M"},"age":32,"hispanic":0.00873,"other":0.00018,"black":2.0e-5,"white":0.99105,"glasses":"None"},"face_id":1,"quality":0.20397,"roll":0}]}]}