{"images":[{"status":"Complete","width":2916,"height":1800,"file":"6HlWOnOpCgD9RQMKqHD92Ts_4_IL94pptKlkDx66JEogRcyHPdrgONo1JnOJOwETjfec_78YbCdMETiWPq88IxfG9NA=s0","faces":[{"topLeftX":1627,"topLeftY":648,"chinTipX":1656,"rightEyeCenterX":1647,"yaw":-18,"chinTipY":719,"confidence":0.99988,"height":66,"rightEyeCenterY":663,"width":66,"leftEyeCenterY":666,"leftEyeCenterX":1674,"pitch":-5,"attributes":{"lips":"Apart","asian":0.00936,"gender":{"type":"F"},"age":39,"hispanic":0.06224,"other":0.01176,"black":0.66947,"white":0.24718,"glasses":"None"},"face_id":1,"quality":-0.92087,"roll":4},{"topLeftX":1226,"topLeftY":612,"chinTipX":1276,"rightEyeCenterX":1258,"yaw":-21,"chinTipY":714,"confidence":0.9998,"height":102,"rightEyeCenterY":634,"width":102,"leftEyeCenterY":641,"leftEyeCenterX":1301,"pitch":16,"attributes":{"lips":"Together","asian":0.00129,"gender":{"type":"M"},"age":34,"hispanic":0.01217,"other":0.00543,"black":0.01711,"white":0.964,"glasses":"None"},"face_id":2,"quality":-2.0693,"roll":3},{"topLeftX":1744,"topLeftY":658,"chinTipX":1784,"rightEyeCenterX":1767,"yaw":-4,"chinTipY":730,"confidence":0.99895,"height":72,"rightEyeCenterY":677,"width":72,"leftEyeCenterY":676,"leftEyeCenterX":1798,"pitch":-15,"attributes":{"lips":"Together","asian":0.04229,"gender":{"type":"M"},"age":42,"hispanic":0.30258,"other":0.02265,"black":0.24282,"white":0.38966,"glasses":"None"},"face_id":3,"quality":-1.30606,"roll":-2}]}]}