{"images":[{"status":"Complete","width":2124,"height":2560,"file":"-mOrTBnJxWY5PoUpIUXIob3FPU9xmub3ge-GNRk8FNoEGgX8clLyt-Lhd7hvhnmkNx8rcY59rKL2GNyYyRkJDDnouITt=s0","faces":[{"topLeftX":907,"topLeftY":556,"chinTipX":1072,"rightEyeCenterX":997,"yaw":-41,"chinTipY":843,"confidence":0.99946,"height":288,"rightEyeCenterY":629,"width":288,"leftEyeCenterY":630,"leftEyeCenterX":1115,"pitch":5,"attributes":{"lips":"Together","asian":0.24673,"gender":{"type":"F"},"age":27,"hispanic":0.12516,"other":0.02933,"black":0.00555,"white":0.59322,"glasses":"None"},"face_id":1,"quality":-0.09596,"roll":-4}]}]}