{"images":[{"status":"Complete","width":1879,"height":2500,"file":"TkcVgU1HzOsMKExjAI0YZzvhVdnrpM7WV4p8WBff4s2PiovYK9W70R2DwOvR8qGAoaeC6fAWraE5DZY3iWrGrIW7lw=s0","faces":[{"topLeftX":646,"topLeftY":452,"chinTipX":759,"rightEyeCenterX":707,"yaw":13,"chinTipY":714,"confidence":0.99998,"height":247,"rightEyeCenterY":519,"width":247,"leftEyeCenterY":516,"leftEyeCenterX":806,"pitch":2,"attributes":{"lips":"Apart","asian":0.01185,"gender":{"type":"M"},"age":42,"hispanic":0.19944,"other":0.00258,"black":0.00027,"white":0.78586,"glasses":"None"},"face_id":1,"quality":0.67928,"roll":-1},{"topLeftX":21,"topLeftY":1684,"chinTipX":130,"rightEyeCenterX":79,"yaw":-10,"chinTipY":1902,"confidence":0.98386,"height":209,"rightEyeCenterY":1739,"width":209,"leftEyeCenterY":1738,"leftEyeCenterX":171,"pitch":-12,"attributes":{"lips":"Apart","asian":0.00284,"gender":{"type":"M"},"age":42,"hispanic":0.18165,"other":0.00799,"black":0.00651,"white":0.80101,"glasses":"Sun"},"face_id":2,"quality":-3.20356,"roll":-2},{"topLeftX":817,"topLeftY":795,"chinTipX":841,"rightEyeCenterX":833,"yaw":-11,"chinTipY":845,"confidence":0.98297,"height":52,"rightEyeCenterY":807,"width":52,"leftEyeCenterY":809,"leftEyeCenterX":851,"pitch":8,"attributes":{"lips":"Apart","asian":0.05877,"gender":{"type":"M"},"age":24,"hispanic":0.35973,"other":0.11931,"black":0.16135,"white":0.30085,"glasses":"None"},"face_id":3,"quality":-1.84094,"roll":1}]}]}