{"images":[{"status":"Complete","width":2500,"height":1578,"file":"L5ivRpLDt0otjl2ahVdu40CD8FEqDg-vBuYDNMNdvW6SVozrUhv5Hl82aM4VZ4I5Raltzn1TTjhCWCeVeNz4AHC8bh0=s0","faces":[{"topLeftX":918,"topLeftY":652,"chinTipX":957,"rightEyeCenterX":935,"yaw":10,"chinTipY":724,"confidence":0.99977,"height":74,"rightEyeCenterY":673,"width":74,"leftEyeCenterY":669,"leftEyeCenterX":962,"pitch":-11,"attributes":{"lips":"Apart","asian":0.03078,"gender":{"type":"M"},"age":30,"hispanic":0.47644,"other":0.02495,"black":0.11515,"white":0.35267,"glasses":"None"},"face_id":1,"quality":-0.0897,"roll":-9}]}]}