{"images":[{"status":"Complete","width":2668,"height":1060,"file":"RdjqahHMJnuusuFn2P0mlxojtTGKKLT0PUfwJ-LL1KrgrViU0HkoGLW7yTdWnIA5U5k_fh-hAIlaVUCal4b5L0sQ84k=s0","faces":[{"topLeftX":372,"topLeftY":297,"chinTipX":398,"rightEyeCenterX":387,"yaw":8,"chinTipY":363,"confidence":0.99979,"height":62,"rightEyeCenterY":314,"width":62,"leftEyeCenterY":315,"leftEyeCenterX":416,"pitch":-13,"attributes":{"lips":"Together","asian":0.0516,"gender":{"type":"F"},"age":27,"hispanic":0.33472,"other":0.15484,"black":0.02647,"white":0.43236,"glasses":"None"},"face_id":1,"quality":-2.48479,"roll":4}]}]}