{"images":[{"status":"Complete","width":2500,"height":2022,"file":"LhQYA150fC66lW9HYVXuYVbqh4k1KN13TId4L9HA4lx5CsORnbyDgyZ-nKtr66rKicJ0ngsR5-q9LBPPwcPNJqxj-5I=s0","faces":[{"topLeftX":1188,"topLeftY":680,"chinTipX":1234,"rightEyeCenterX":1221,"yaw":9,"chinTipY":785,"confidence":0.99931,"height":103,"rightEyeCenterY":701,"width":103,"leftEyeCenterY":710,"leftEyeCenterX":1270,"pitch":-15,"attributes":{"lips":"Together","asian":0.03861,"gender":{"type":"F"},"age":34,"hispanic":0.1936,"other":0.00607,"black":0.01158,"white":0.75013,"glasses":"None"},"face_id":1,"quality":-1.41799,"roll":8},{"topLeftX":1774,"topLeftY":608,"chinTipX":1828,"rightEyeCenterX":1805,"yaw":5,"chinTipY":729,"confidence":0.99906,"height":112,"rightEyeCenterY":637,"width":112,"leftEyeCenterY":640,"leftEyeCenterX":1860,"pitch":-30,"attributes":{"lips":"Together","asian":0.00076,"gender":{"type":"M"},"age":35,"hispanic":0.00814,"other":0.00126,"black":0.00193,"white":0.98791,"glasses":"None"},"face_id":2,"quality":-2.93585,"roll":3}]}]}