{"images":[{"status":"Complete","width":2010,"height":2500,"file":"m8QIFjI3LFikFf1tS6UCCdYDmGhK2jOMixA7PX5QLL5-dyuVt-YVQho5rhzxD2uFMZkIkJ1KopeiZ5FI3wytFovEZw=s0","faces":[{"topLeftX":797,"topLeftY":152,"chinTipX":835,"rightEyeCenterX":813,"yaw":7,"chinTipY":215,"confidence":0.99907,"height":62,"rightEyeCenterY":171,"width":62,"leftEyeCenterY":164,"leftEyeCenterX":840,"pitch":6,"attributes":{"lips":"Together","asian":0.12581,"gender":{"type":"F"},"age":20,"hispanic":0.18135,"other":0.02956,"black":0.43457,"white":0.22873,"glasses":"Eye"},"face_id":1,"quality":-1.7644,"roll":-10},{"topLeftX":906,"topLeftY":1100,"chinTipX":965,"rightEyeCenterX":926,"yaw":-22,"chinTipY":1189,"confidence":0.99581,"height":88,"rightEyeCenterY":1125,"width":88,"leftEyeCenterY":1117,"leftEyeCenterX":963,"pitch":12,"attributes":{"lips":"Apart","asian":0.00226,"gender":{"type":"M"},"age":42,"hispanic":0.0931,"other":0.00209,"black":0.00522,"white":0.89733,"glasses":"None"},"face_id":2,"quality":-0.78112,"roll":-17},{"topLeftX":79,"topLeftY":922,"chinTipX":113,"rightEyeCenterX":110,"yaw":-19,"chinTipY":997,"confidence":0.99434,"height":71,"rightEyeCenterY":935,"width":71,"leftEyeCenterY":943,"leftEyeCenterX":138,"pitch":15,"attributes":{"lips":"Apart","asian":0.91237,"gender":{"type":"M"},"age":46,"hispanic":0.02176,"other":0.02288,"black":0.01285,"white":0.03014,"glasses":"Eye"},"face_id":3,"quality":-2.7068,"roll":11},{"topLeftX":1021,"topLeftY":1491,"chinTipX":1044,"rightEyeCenterX":1038,"yaw":18,"chinTipY":1553,"confidence":0.99413,"height":62,"rightEyeCenterY":1509,"width":62,"leftEyeCenterY":1510,"leftEyeCenterX":1062,"pitch":40,"attributes":{"lips":"Apart","asian":0.01968,"gender":{"type":"M"},"age":35,"hispanic":0.16171,"other":0.01834,"black":0.04041,"white":0.75986,"glasses":"Eye"},"face_id":4,"quality":-2.34436,"roll":7}]}]}