{"images":[{"status":"Complete","width":2856,"height":2111,"file":"LawGihKdukH3j3t6GE1vXXYVvKPgA9lriyvAvYX3Vx5IWGQc9Ous_tHHpaDkRF10TXhbnsRSTfZVvIgCwZOL4_SbzDqC=s0","faces":[{"topLeftX":2310,"topLeftY":1214,"chinTipX":2330,"rightEyeCenterX":2324,"yaw":10,"chinTipY":1256,"confidence":0.993,"height":42,"rightEyeCenterY":1224,"width":42,"leftEyeCenterY":1225,"leftEyeCenterX":2341,"pitch":-2,"attributes":{"lips":"Together","asian":0.01597,"gender":{"type":"M"},"age":37,"hispanic":0.09885,"other":0.00891,"black":0.01877,"white":0.85751,"glasses":"None"},"face_id":1,"quality":-2.17692,"roll":4}]}]}