{"images":[{"status":"Complete","width":1896,"height":2712,"file":"Vp0Hfhn4p_GHO8o25knJrIYvD0bj9FjNzYCnBP0XdzjWrmMH3ISevu_an-wwNn_UfapNktiPkImGsx0TiR-oId00kquD=s0","faces":[{"topLeftX":863,"topLeftY":1202,"chinTipX":982,"rightEyeCenterX":914,"yaw":-22,"chinTipY":1405,"confidence":0.99836,"height":202,"rightEyeCenterY":1251,"width":202,"leftEyeCenterY":1237,"leftEyeCenterX":1001,"pitch":-7,"attributes":{"lips":"Together","asian":0.00051,"gender":{"type":"F"},"age":44,"hispanic":0.01011,"other":0.00038,"black":0.00146,"white":0.98754,"glasses":"None"},"face_id":1,"quality":-1.31344,"roll":-8}]}]}